Calculator_Package/__init__.py
Calculator_Package/main.py
calculator_decorator/__init__.py
calculator_decorator/main.py
calculator_decorator-1.0.dist-info/METADATA
calculator_decorator-1.0.dist-info/WHEEL
calculator_decorator-1.0.dist-info/entry_points.txt
calculator_decorator-1.0.dist-info/top_level.txt
calculator_decorator-1.0.dist-info/RECORD
