Metadata-Version: 2.1
Name: calculator-decorator
Version: 1.0
Summary: calculator operaions
Home-page: UNKNOWN
Author: ahmed atef
Author-email: ahmedatef93legend@gmail.com
License: UNKNOWN
Platform: UNKNOWN
